sisicepy/__init__.py
sisicepy/spectrogram/processing.py
sisicepy/spectrogram/spectrogram.py
sisicepy/traces/__init__.py
sisicepy/traces/captor/digos.py
sisicepy/traces/captor/geobit.py
sisicepy/traces/io/datacube_loader.py
sisicepy/traces/io/mseed_loader.py
sisicepy/traces/recorder/datacube.py
sisicepy/traces/signal/freq_filter.py
sisicepy/traces/signal/processing.py
sisicepy/traces/signal/utils.py
sisicepy/traces/traces.py
sisicepy-0.2.4.1.dist-info/METADATA
sisicepy-0.2.4.1.dist-info/WHEEL
sisicepy-0.2.4.1.dist-info/licenses/LICENSE
sisicepy-0.2.4.1.dist-info/RECORD
